spellbook_serve_client/__init__.py
spellbook_serve_client/api_engine.py
spellbook_serve_client/client.py
spellbook_serve_client/completion.py
spellbook_serve_client/data_types.py
spellbook_serve_client/errors.py
spellbook_serve_client/fine_tuning.py
spellbook_serve_client/model.py
spellbook_serve_client/types.py
spellbook_serve_client-0.0.0a1.dist-info/METADATA
spellbook_serve_client-0.0.0a1.dist-info/WHEEL
spellbook_serve_client-0.0.0a1.dist-info/RECORD
