Metadata-Version: 2.1
Name: spellbook-serve-client
Version: 0.0.0a1
Summary: Spellbok Serve Python Client
Home-page: https://scaleapi.github.io/spellbook-serve/
License: Apache-2.0
Author: Phil Chen
Author-email: phil.chen@scale.com
Maintainer: Phil Chen
Maintainer-email: phil.chen@scale.com
Requires-Python: >=3.7,<4.0
Classifier: License :: OSI Approved :: Apache Software License
Classifier: Programming Language :: Python :: 3
Classifier: Programming Language :: Python :: 3.7
Classifier: Programming Language :: Python :: 3.8
Classifier: Programming Language :: Python :: 3.9
Classifier: Programming Language :: Python :: 3.10
Classifier: Programming Language :: Python :: 3.11
Requires-Dist: aiohttp (>=3.8,<4.0)
Requires-Dist: pydantic (>=1.10,<2.0)
Requires-Dist: requests (>=2.31.0,<3.0.0)
Project-URL: Repository, https://github.com/scaleapi/spellbook-serve
